djangoldp_notification/__init__.py
djangoldp_notification/admin.py
djangoldp_notification/apps.py
djangoldp_notification/check_integrity.py
djangoldp_notification/djangoldp_settings.py
djangoldp_notification/factories.py
djangoldp_notification/middlewares.py
djangoldp_notification/models.py
djangoldp_notification/settings.py
djangoldp_notification/views.py
djangoldp_notification/locale/en/LC_MESSAGES/django.mo
djangoldp_notification/locale/en/LC_MESSAGES/django.po
djangoldp_notification/locale/es/LC_MESSAGES/django.mo
djangoldp_notification/locale/es/LC_MESSAGES/django.po
djangoldp_notification/locale/fr/LC_MESSAGES/django.mo
djangoldp_notification/locale/fr/LC_MESSAGES/django.po
djangoldp_notification/management/commands/__init__.py
djangoldp_notification/management/commands/create_subscriptions.py
djangoldp_notification/management/commands/mock_notification.py
djangoldp_notification/management/commands/suppress_old_notifications.py
djangoldp_notification/migrations/0001_initial.py
djangoldp_notification/migrations/0002_auto_20190917_1107.py
djangoldp_notification/migrations/0003_auto_20200429_1346.py
djangoldp_notification/migrations/0004_auto_20200501_1207.py
djangoldp_notification/migrations/0005_auto_20200505_1733.py
djangoldp_notification/migrations/0006_subscription_parent.py
djangoldp_notification/migrations/0007_auto_20200604_1055.py
djangoldp_notification/migrations/0008_auto_20200610_1323.py
djangoldp_notification/migrations/0009_auto_20200619_0802.py
djangoldp_notification/migrations/0010_notificationsetting.py
djangoldp_notification/migrations/0011_auto_20210218_1145.py
djangoldp_notification/migrations/0012_auto_20210729_1912.py
djangoldp_notification/migrations/0013_auto_20211016_1203.py
djangoldp_notification/migrations/0014_subscription_disable_automatic_notifications.py
djangoldp_notification/migrations/0015_alter_subscription_options.py
djangoldp_notification/migrations/0016_alter_notification_options_and_more.py
djangoldp_notification-5.0.0.dist-info/METADATA
djangoldp_notification-5.0.0.dist-info/WHEEL
djangoldp_notification-5.0.0.dist-info/top_level.txt
djangoldp_notification-5.0.0.dist-info/RECORD
