Metadata-Version: 2.4
Name: djangoldp_notification
Version: 5.0.0
Summary: djangoldp package for notifications data models
Home-page: https://git.happy-dev.fr/startinblox/djangoldp-packages/djangoldp-notifications
Author: Startin'blox
Author-email: matthieu@happy-dev.fr
License: MIT
Requires-Dist: djangoldp~=5.0.0
Requires-Dist: djangoldp_account~=5.0.0
Provides-Extra: include-package-data
Requires-Dist: True; extra == "include-package-data"
Provides-Extra: dev
Requires-Dist: factory_boy>=2.12.0; extra == "dev"
